{
    "thoughts": {
        "text": "I think I can use the `get_hyperlinks` command to extract hyperlinks from a webpage.",
        "reasoning": "I want to extract hyperlinks from a webpage. The `get_hyperlinks` command can be used to extract hyperlinks from a webpage.",
        "plan": "- Use the `get_hyperlinks` command with the url argument of the webpage to extract hyperlinks from.",
        "criticism": "I should make sure that the url argument is a valid URL.",
        "speak": "I will use the `get_hyperlinks` command to extract hyperlinks from a webpage."
    },
    "command": {
        "name": "get_hyperlinks",
        "args": {
            "url": "https://en.wikipedia.org/wiki/Python_(programming_language)"
        }
    }
}