{
    "thoughts": {
        "text": "I think I should use the 'append_to_file' command to add some more text to the 'new_file.txt' file.",
        "reasoning": "This will allow me to add more information to the file without overwriting the existing text.",
        "plan": "- Use the 'append_to_file' command to add some more text to the 'new_file.txt' file",
        "criticism": "I should have thought of this earlier, as it would have allowed me to add more information to the file without overwriting the existing text.",
        "speak": "I will use the 'append_to_file' command to add some more text to the 'new_file.txt' file."
    },
    "command": {
        "name": "append_to_file",
        "args": {
            "filename": "/home/atlas/autogpt/auto_gpt_workspace/new_file.txt",
            "text": "This is some more text that I am adding to the file."
        }
    }
}