{
    "thoughts": {
        "text": "I think I can use the 'list_files' command to check if the file exists before attempting to read it.",
        "reasoning": "It is important to always verify that a file exists before attempting to read it to avoid errors.",
        "plan": "- Use the 'list_files' command to check if the file exists.\n- If the file exists, use the 'read_file' command to read the file.",
        "criticism": "I should have used the 'list_files' command before attempting to read the file.",
        "speak": "I will use the 'list_files' command to check if the file exists before attempting to read it."
    },
    "command": {
        "name": "list_files",
        "args": {
            "directory": "/home/atlas/autogpt/auto_gpt_workspace"
        }
    }
}