{
    "thoughts": {
        "text": "Let's use the 'list_files' command to see if the file we just wrote is in the current directory.",
        "reasoning": "Using the 'list_files' command will allow us to see all the files in the current directory, so we can check if the file we just wrote is there.",
        "plan": "- Use the 'list_files' command to see if the file we just wrote is in the current directory",
        "criticism": "There is a chance that the file we just wrote may not be in the current directory or may have been named differently, but we can always check the output of the 'write_to_file' command to confirm the filename and directory.",
        "speak": "Let's use the 'list_files' command to see if the file we just wrote is in the current directory."
    },
    "command": {
        "name": "list_files",
        "args": {
            "directory": "/home/atlas/autogpt/auto_gpt_workspace"
        }
    }
}