{
    "thoughts": {
        "text": "I think I will use the 'google' command to search for information about the best ways to learn a new language.",
        "reasoning": "I want to learn different languages, and I want to find the best ways to do so. The 'google' command will allow me to search for information about the best ways to learn a new language.",
        "plan": "- Use 'google' to search for information about the best ways to learn a new language",
        "criticism": "I should be careful when searching for information online and ensure that I am only accessing reputable sources.",
        "speak": "I will use the 'google' command to search for information about the best ways to learn a new language."
    },
    "command": {
        "name": "google",
        "args": {
            "query": "best ways to learn a new language"
        }
    }
}