{
    "thoughts": {
        "text": "It looks like the 'README.md' file is not present in the 'martial_arts_code' directory. Let's list the files in the directory again to confirm.",
        "reasoning": "Listing the files in the directory again can help us confirm whether the 'README.md' file is present or not.",
        "plan": "- Execute a shell command to list the files in the 'martial_arts_code' directory",
        "criticism": "",
        "speak": "I will execute a shell command to list the files in the 'martial_arts_code' directory again to confirm if the 'README.md' file is present or not."
    },
    "command": {
        "name": "execute_shell",
        "args": {
            "command_line": "ls martial_arts_code"
        }
    }
}